AmazonTicoTool/__init__.py
AmazonTicoTool-0.3.dist-info/LICENCE.txt
AmazonTicoTool-0.3.dist-info/METADATA
AmazonTicoTool-0.3.dist-info/WHEEL
AmazonTicoTool-0.3.dist-info/top_level.txt
AmazonTicoTool-0.3.dist-info/RECORD
