Metadata-Version: 2.1
Name: AmazonTicoTool
Version: 0.3
Summary: Tico package to extrack the following tables Buyablility_Status, General_information, Hazmat, Recall
Home-page: UNKNOWN
Author: Vijaykumar Raman
Author-email: ramaviji@amazon.com
License: UNKNOWN
Platform: UNKNOWN
License-File: LICENCE.txt
